{"metadata": {"dbt_schema_version": "https://schemas.getdbt.com/dbt/run-results/v4.json", "dbt_version": "1.5.6", "generated_at": "2023-09-05T23:42:24.290256Z", "invocation_id": "7ef811f5-86d9-4024-b591-7243a3f3b853", "env": {}}, "results": [{"status": "success", "timing": [{"name": "compile", "started_at": "2023-09-05T23:42:22.303688Z", "completed_at": "2023-09-05T23:42:22.335079Z"}, {"name": "execute", "started_at": "2023-09-05T23:42:22.350841Z", "completed_at": "2023-09-05T23:42:22.350857Z"}], "thread_id": "Thread-1", "execution_time": 0.05544018745422363, "adapter_response": {}, "message": null, "failures": null, "unique_id": "model.twitter_ads_source.stg_twitter_ads__account_history_tmp"}, {"status": "success", "timing": [{"name": "compile", "started_at": "2023-09-05T23:42:22.330890Z", "completed_at": "2023-09-05T23:42:22.337365Z"}, {"name": "execute", "started_at": "2023-09-05T23:42:22.359714Z", "completed_at": "2023-09-05T23:42:22.359720Z"}], "thread_id": "Thread-2", "execution_time": 0.04520726203918457, "adapter_response": {}, "message": null, "failures": null, "unique_id": "model.twitter_ads_source.stg_twitter_ads__campaign_history_tmp"}, {"status": "success", "timing": [{"name": "compile", "started_at": "2023-09-05T23:42:22.337769Z", "completed_at": "2023-09-05T23:42:22.358722Z"}, {"name": "execute", "started_at": "2023-09-05T23:42:22.362582Z", "completed_at": "2023-09-05T23:42:22.362587Z"}], "thread_id": "Thread-3", "execution_time": 0.03460502624511719, "adapter_response": {}, "message": null, "failures": null, "unique_id": "model.twitter_ads_source.stg_twitter_ads__campaign_report_tmp"}, {"status": "success", "timing": [{"name": "compile", "started_at": "2023-09-05T23:42:22.340844Z", "completed_at": "2023-09-05T23:42:22.359017Z"}, {"name": "execute", "started_at": "2023-09-05T23:42:22.362806Z", "completed_at": "2023-09-05T23:42:22.362809Z"}], "thread_id": "Thread-4", "execution_time": 0.03454279899597168, "adapter_response": {}, "message": null, "failures": null, "unique_id": "model.twitter_ads_source.stg_twitter_ads__line_item_history_tmp"}, {"status": "success", "timing": [{"name": "compile", "started_at": "2023-09-05T23:42:22.348098Z", "completed_at": "2023-09-05T23:42:22.359278Z"}, {"name": "execute", "started_at": "2023-09-05T23:42:22.363190Z", "completed_at": "2023-09-05T23:42:22.363193Z"}], "thread_id": "Thread-6", "execution_time": 0.03083181381225586, "adapter_response": {}, "message": null, "failures": null, "unique_id": "model.twitter_ads_source.stg_twitter_ads__line_item_report_tmp"}, {"status": "success", "timing": [{"name": "compile", "started_at": "2023-09-05T23:42:22.343789Z", "completed_at": "2023-09-05T23:42:22.359497Z"}, {"name": "execute", "started_at": "2023-09-05T23:42:22.363403Z", "completed_at": "2023-09-05T23:42:22.363406Z"}], "thread_id": "Thread-5", "execution_time": 0.031778812408447266, "adapter_response": {}, "message": null, "failures": null, "unique_id": "model.twitter_ads_source.stg_twitter_ads__line_item_keywords_report_tmp"}, {"status": "success", "timing": [{"name": "compile", "started_at": "2023-09-05T23:42:22.351125Z", "completed_at": "2023-09-05T23:42:22.360314Z"}, {"name": "execute", "started_at": "2023-09-05T23:42:22.364053Z", "completed_at": "2023-09-05T23:42:22.364056Z"}], "thread_id": "Thread-7", "execution_time": 0.03428983688354492, "adapter_response": {}, "message": null, "failures": null, "unique_id": "model.twitter_ads_source.stg_twitter_ads__promoted_tweet_history_tmp"}, {"status": "success", "timing": [{"name": "compile", "started_at": "2023-09-05T23:42:22.354871Z", "completed_at": "2023-09-05T23:42:22.361003Z"}, {"name": "execute", "started_at": "2023-09-05T23:42:22.365135Z", "completed_at": "2023-09-05T23:42:22.365138Z"}], "thread_id": "Thread-8", "execution_time": 0.03492021560668945, "adapter_response": {}, "message": null, "failures": null, "unique_id": "model.twitter_ads_source.stg_twitter_ads__promoted_tweet_report_tmp"}, {"status": "success", "timing": [{"name": "compile", "started_at": "2023-09-05T23:42:22.366499Z", "completed_at": "2023-09-05T23:42:22.373476Z"}, {"name": "execute", "started_at": "2023-09-05T23:42:22.384186Z", "completed_at": "2023-09-05T23:42:22.384193Z"}], "thread_id": "Thread-1", "execution_time": 0.026279211044311523, "adapter_response": {}, "message": null, "failures": null, "unique_id": "model.twitter_ads_source.stg_twitter_ads__tweet_tmp"}, {"status": "success", "timing": [{"name": "compile", "started_at": "2023-09-05T23:42:22.379313Z", "completed_at": "2023-09-05T23:42:22.380363Z"}, {"name": "execute", "started_at": "2023-09-05T23:42:22.388979Z", "completed_at": "2023-09-05T23:42:22.388982Z"}], "thread_id": "Thread-3", "execution_time": 0.01867389678955078, "adapter_response": {}, "message": null, "failures": null, "unique_id": "seed.twitter_integration_tests.twitter_account_history_data"}, {"status": "success", "timing": [{"name": "compile", "started_at": "2023-09-05T23:42:22.380689Z", "completed_at": "2023-09-05T23:42:22.381636Z"}, {"name": "execute", "started_at": "2023-09-05T23:42:22.389173Z", "completed_at": "2023-09-05T23:42:22.389177Z"}], "thread_id": "Thread-4", "execution_time": 0.01869487762451172, "adapter_response": {}, "message": null, "failures": null, "unique_id": "seed.twitter_integration_tests.twitter_account_report_data"}, {"status": "success", "timing": [{"name": "compile", "started_at": "2023-09-05T23:42:22.374028Z", "completed_at": "2023-09-05T23:42:22.382157Z"}, {"name": "execute", "started_at": "2023-09-05T23:42:22.389538Z", "completed_at": "2023-09-05T23:42:22.389541Z"}], "thread_id": "Thread-2", "execution_time": 0.025599956512451172, "adapter_response": {}, "message": null, "failures": null, "unique_id": "model.twitter_ads_source.stg_twitter_ads__tweet_url_tmp"}, {"status": "success", "timing": [{"name": "compile", "started_at": "2023-09-05T23:42:22.382372Z", "completed_at": "2023-09-05T23:42:22.383959Z"}, {"name": "execute", "started_at": "2023-09-05T23:42:22.389732Z", "completed_at": "2023-09-05T23:42:22.389735Z"}], "thread_id": "Thread-6", "execution_time": 0.019117116928100586, "adapter_response": {}, "message": null, "failures": null, "unique_id": "seed.twitter_integration_tests.twitter_campaign_history_data"}, {"status": "success", "timing": [{"name": "compile", "started_at": "2023-09-05T23:42:22.384401Z", "completed_at": "2023-09-05T23:42:22.385241Z"}, {"name": "execute", "started_at": "2023-09-05T23:42:22.390203Z", "completed_at": "2023-09-05T23:42:22.390206Z"}], "thread_id": "Thread-5", "execution_time": 0.019221067428588867, "adapter_response": {}, "message": null, "failures": null, "unique_id": "seed.twitter_integration_tests.twitter_campaign_report_data"}, {"status": "success", "timing": [{"name": "compile", "started_at": "2023-09-05T23:42:22.385466Z", "completed_at": "2023-09-05T23:42:22.386241Z"}, {"name": "execute", "started_at": "2023-09-05T23:42:22.390399Z", "completed_at": "2023-09-05T23:42:22.390401Z"}], "thread_id": "Thread-7", "execution_time": 0.016122817993164062, "adapter_response": {}, "message": null, "failures": null, "unique_id": "seed.twitter_integration_tests.twitter_line_item_history_data"}, {"status": "success", "timing": [{"name": "compile", "started_at": "2023-09-05T23:42:22.386803Z", "completed_at": "2023-09-05T23:42:22.387606Z"}, {"name": "execute", "started_at": "2023-09-05T23:42:22.391430Z", "completed_at": "2023-09-05T23:42:22.391433Z"}], "thread_id": "Thread-8", "execution_time": 0.0162508487701416, "adapter_response": {}, "message": null, "failures": null, "unique_id": "seed.twitter_integration_tests.twitter_line_item_keywords_report_data"}, {"status": "success", "timing": [{"name": "compile", "started_at": "2023-09-05T23:42:22.396969Z", "completed_at": "2023-09-05T23:42:22.398038Z"}, {"name": "execute", "started_at": "2023-09-05T23:42:22.405597Z", "completed_at": "2023-09-05T23:42:22.405604Z"}], "thread_id": "Thread-1", "execution_time": 0.029092073440551758, "adapter_response": {}, "message": null, "failures": null, "unique_id": "seed.twitter_integration_tests.twitter_line_item_report_data"}, {"status": "success", "timing": [{"name": "compile", "started_at": "2023-09-05T23:42:22.400197Z", "completed_at": "2023-09-05T23:42:22.401041Z"}, {"name": "execute", "started_at": "2023-09-05T23:42:22.422201Z", "completed_at": "2023-09-05T23:42:22.422205Z"}], "thread_id": "Thread-3", "execution_time": 0.02830791473388672, "adapter_response": {}, "message": null, "failures": null, "unique_id": "seed.twitter_integration_tests.twitter_promoted_tweet_history_data"}, {"status": "success", "timing": [{"name": "compile", "started_at": "2023-09-05T23:42:22.401246Z", "completed_at": "2023-09-05T23:42:22.402043Z"}, {"name": "execute", "started_at": "2023-09-05T23:42:22.422399Z", "completed_at": "2023-09-05T23:42:22.422402Z"}], "thread_id": "Thread-4", "execution_time": 0.028423070907592773, "adapter_response": {}, "message": null, "failures": null, "unique_id": "seed.twitter_integration_tests.twitter_promoted_tweet_report_data"}, {"status": "success", "timing": [{"name": "compile", "started_at": "2023-09-05T23:42:22.402417Z", "completed_at": "2023-09-05T23:42:22.404158Z"}, {"name": "execute", "started_at": "2023-09-05T23:42:22.422737Z", "completed_at": "2023-09-05T23:42:22.422740Z"}], "thread_id": "Thread-2", "execution_time": 0.028554916381835938, "adapter_response": {}, "message": null, "failures": null, "unique_id": "seed.twitter_integration_tests.twitter_tweet_data"}, {"status": "success", "timing": [{"name": "compile", "started_at": "2023-09-05T23:42:22.404449Z", "completed_at": "2023-09-05T23:42:22.405351Z"}, {"name": "execute", "started_at": "2023-09-05T23:42:22.422925Z", "completed_at": "2023-09-05T23:42:22.422928Z"}], "thread_id": "Thread-6", "execution_time": 0.0286409854888916, "adapter_response": {}, "message": null, "failures": null, "unique_id": "seed.twitter_integration_tests.twitter_tweet_url_data"}, {"status": "success", "timing": [{"name": "compile", "started_at": "2023-09-05T23:42:22.412590Z", "completed_at": "2023-09-05T23:42:23.193628Z"}, {"name": "execute", "started_at": "2023-09-05T23:42:23.194854Z", "completed_at": "2023-09-05T23:42:23.194858Z"}], "thread_id": "Thread-7", "execution_time": 0.8678719997406006, "adapter_response": {}, "message": null, "failures": null, "unique_id": "model.twitter_ads_source.stg_twitter_ads__campaign_history"}, {"status": "success", "timing": [{"name": "compile", "started_at": "2023-09-05T23:42:22.464022Z", "completed_at": "2023-09-05T23:42:23.194056Z"}, {"name": "execute", "started_at": "2023-09-05T23:42:23.195252Z", "completed_at": "2023-09-05T23:42:23.195255Z"}], "thread_id": "Thread-6", "execution_time": 0.8387668132781982, "adapter_response": {}, "message": null, "failures": null, "unique_id": "model.twitter_ads_source.stg_twitter_ads__promoted_tweet_report"}, {"status": "success", "timing": [{"name": "compile", "started_at": "2023-09-05T23:42:22.405814Z", "completed_at": "2023-09-05T23:42:23.193349Z"}, {"name": "execute", "started_at": "2023-09-05T23:42:23.194465Z", "completed_at": "2023-09-05T23:42:23.194472Z"}], "thread_id": "Thread-5", "execution_time": 0.8692748546600342, "adapter_response": {}, "message": null, "failures": null, "unique_id": "model.twitter_ads_source.stg_twitter_ads__account_history"}, {"status": "success", "timing": [{"name": "compile", "started_at": "2023-09-05T23:42:23.279067Z", "completed_at": "2023-09-05T23:42:23.287860Z"}, {"name": "execute", "started_at": "2023-09-05T23:42:23.288259Z", "completed_at": "2023-09-05T23:42:23.288264Z"}], "thread_id": "Thread-5", "execution_time": 0.019253015518188477, "adapter_response": {}, "message": null, "failures": null, "unique_id": "test.twitter_ads_source.dbt_utils_unique_combination_of_columns_stg_twitter_ads__campaign_history_source_relation__campaign_id__updated_timestamp.9b0c16487d"}, {"status": "success", "timing": [{"name": "compile", "started_at": "2023-09-05T23:42:23.289572Z", "completed_at": "2023-09-05T23:42:23.295061Z"}, {"name": "execute", "started_at": "2023-09-05T23:42:23.295661Z", "completed_at": "2023-09-05T23:42:23.295666Z"}], "thread_id": "Thread-5", "execution_time": 0.006967067718505859, "adapter_response": {}, "message": null, "failures": null, "unique_id": "test.twitter_ads_source.not_null_stg_twitter_ads__campaign_history_campaign_id.51218487ce"}, {"status": "success", "timing": [{"name": "compile", "started_at": "2023-09-05T23:42:22.416726Z", "completed_at": "2023-09-05T23:42:23.243380Z"}, {"name": "execute", "started_at": "2023-09-05T23:42:23.243783Z", "completed_at": "2023-09-05T23:42:23.243788Z"}], "thread_id": "Thread-8", "execution_time": 0.8972949981689453, "adapter_response": {}, "message": null, "failures": null, "unique_id": "model.twitter_ads_source.stg_twitter_ads__campaign_report"}, {"status": "success", "timing": [{"name": "compile", "started_at": "2023-09-05T23:42:22.460511Z", "completed_at": "2023-09-05T23:42:23.244989Z"}, {"name": "execute", "started_at": "2023-09-05T23:42:23.245352Z", "completed_at": "2023-09-05T23:42:23.245355Z"}], "thread_id": "Thread-2", "execution_time": 0.8777148723602295, "adapter_response": {}, "message": null, "failures": null, "unique_id": "model.twitter_ads_source.stg_twitter_ads__promoted_tweet_history"}, {"status": "success", "timing": [{"name": "compile", "started_at": "2023-09-05T23:42:23.298206Z", "completed_at": "2023-09-05T23:42:23.304236Z"}, {"name": "execute", "started_at": "2023-09-05T23:42:23.305186Z", "completed_at": "2023-09-05T23:42:23.305190Z"}], "thread_id": "Thread-5", "execution_time": 0.008961915969848633, "adapter_response": {}, "message": null, "failures": null, "unique_id": "test.twitter_ads_source.dbt_utils_unique_combination_of_columns_stg_twitter_ads__promoted_tweet_report_source_relation__date_day__promoted_tweet_id__placement.9d96bf07d3"}, {"status": "success", "timing": [{"name": "compile", "started_at": "2023-09-05T23:42:23.301757Z", "completed_at": "2023-09-05T23:42:23.304459Z"}, {"name": "execute", "started_at": "2023-09-05T23:42:23.305823Z", "completed_at": "2023-09-05T23:42:23.305827Z"}], "thread_id": "Thread-8", "execution_time": 0.009250879287719727, "adapter_response": {}, "message": null, "failures": null, "unique_id": "test.twitter_ads_source.not_null_stg_twitter_ads__promoted_tweet_report_date_day.c4c46a5894"}, {"status": "success", "timing": [{"name": "compile", "started_at": "2023-09-05T23:42:22.428415Z", "completed_at": "2023-09-05T23:42:23.244184Z"}, {"name": "execute", "started_at": "2023-09-05T23:42:23.244566Z", "completed_at": "2023-09-05T23:42:23.244569Z"}], "thread_id": "Thread-1", "execution_time": 0.8986480236053467, "adapter_response": {}, "message": null, "failures": null, "unique_id": "model.twitter_ads_source.stg_twitter_ads__line_item_history"}, {"status": "success", "timing": [{"name": "compile", "started_at": "2023-09-05T23:42:23.318809Z", "completed_at": "2023-09-05T23:42:23.332670Z"}, {"name": "execute", "started_at": "2023-09-05T23:42:23.350789Z", "completed_at": "2023-09-05T23:42:23.350792Z"}], "thread_id": "Thread-2", "execution_time": 0.047811031341552734, "adapter_response": {}, "message": null, "failures": null, "unique_id": "test.twitter_ads_source.not_null_stg_twitter_ads__promoted_tweet_report_placement.c1b1f648b3"}, {"status": "success", "timing": [{"name": "compile", "started_at": "2023-09-05T23:42:23.321507Z", "completed_at": "2023-09-05T23:42:23.345533Z"}, {"name": "execute", "started_at": "2023-09-05T23:42:23.351358Z", "completed_at": "2023-09-05T23:42:23.351361Z"}], "thread_id": "Thread-5", "execution_time": 0.04775404930114746, "adapter_response": {}, "message": null, "failures": null, "unique_id": "test.twitter_ads_source.not_null_stg_twitter_ads__promoted_tweet_report_promoted_tweet_id.6028694598"}, {"status": "success", "timing": [{"name": "compile", "started_at": "2023-09-05T23:42:23.324700Z", "completed_at": "2023-09-05T23:42:23.350371Z"}, {"name": "execute", "started_at": "2023-09-05T23:42:23.356068Z", "completed_at": "2023-09-05T23:42:23.356072Z"}], "thread_id": "Thread-8", "execution_time": 0.048874855041503906, "adapter_response": {}, "message": null, "failures": null, "unique_id": "model.twitter_ads.twitter_ads__account_report"}, {"status": "success", "timing": [{"name": "compile", "started_at": "2023-09-05T23:42:23.351724Z", "completed_at": "2023-09-05T23:42:23.357012Z"}, {"name": "execute", "started_at": "2023-09-05T23:42:23.359279Z", "completed_at": "2023-09-05T23:42:23.359283Z"}], "thread_id": "Thread-1", "execution_time": 0.017248153686523438, "adapter_response": {}, "message": null, "failures": null, "unique_id": "test.twitter_ads_source.dbt_utils_unique_combination_of_columns_stg_twitter_ads__account_history_source_relation__account_id__updated_timestamp.3492933c38"}, {"status": "success", "timing": [{"name": "compile", "started_at": "2023-09-05T23:42:23.359785Z", "completed_at": "2023-09-05T23:42:23.371278Z"}, {"name": "execute", "started_at": "2023-09-05T23:42:23.374817Z", "completed_at": "2023-09-05T23:42:23.374822Z"}], "thread_id": "Thread-2", "execution_time": 0.017946720123291016, "adapter_response": {}, "message": null, "failures": null, "unique_id": "test.twitter_ads_source.not_null_stg_twitter_ads__account_history_account_id.66fb3601e2"}, {"status": "success", "timing": [{"name": "compile", "started_at": "2023-09-05T23:42:23.362280Z", "completed_at": "2023-09-05T23:42:23.371516Z"}, {"name": "execute", "started_at": "2023-09-05T23:42:23.375038Z", "completed_at": "2023-09-05T23:42:23.375042Z"}], "thread_id": "Thread-5", "execution_time": 0.0178830623626709, "adapter_response": {}, "message": null, "failures": null, "unique_id": "model.twitter_ads.twitter_ads__campaign_report"}, {"status": "success", "timing": [{"name": "compile", "started_at": "2023-09-05T23:42:23.367384Z", "completed_at": "2023-09-05T23:42:23.372262Z"}, {"name": "execute", "started_at": "2023-09-05T23:42:23.376316Z", "completed_at": "2023-09-05T23:42:23.376319Z"}], "thread_id": "Thread-8", "execution_time": 0.017817020416259766, "adapter_response": {}, "message": null, "failures": null, "unique_id": "test.twitter_ads_source.dbt_utils_unique_combination_of_columns_stg_twitter_ads__campaign_report_source_relation__date_day__campaign_id__placement.9d5717ee54"}, {"status": "success", "timing": [{"name": "compile", "started_at": "2023-09-05T23:42:23.372462Z", "completed_at": "2023-09-05T23:42:23.376536Z"}, {"name": "execute", "started_at": "2023-09-05T23:42:23.378621Z", "completed_at": "2023-09-05T23:42:23.378625Z"}], "thread_id": "Thread-1", "execution_time": 0.008764982223510742, "adapter_response": {}, "message": null, "failures": null, "unique_id": "test.twitter_ads_source.not_null_stg_twitter_ads__campaign_report_campaign_id.a63b62981f"}, {"status": "success", "timing": [{"name": "compile", "started_at": "2023-09-05T23:42:23.379911Z", "completed_at": "2023-09-05T23:42:23.389170Z"}, {"name": "execute", "started_at": "2023-09-05T23:42:23.393307Z", "completed_at": "2023-09-05T23:42:23.393312Z"}], "thread_id": "Thread-2", "execution_time": 0.016444921493530273, "adapter_response": {}, "message": null, "failures": null, "unique_id": "test.twitter_ads_source.not_null_stg_twitter_ads__campaign_report_date_day.053c09786c"}, {"status": "success", "timing": [{"name": "compile", "started_at": "2023-09-05T23:42:23.382454Z", "completed_at": "2023-09-05T23:42:23.392500Z"}, {"name": "execute", "started_at": "2023-09-05T23:42:23.393872Z", "completed_at": "2023-09-05T23:42:23.393876Z"}], "thread_id": "Thread-5", "execution_time": 0.016943931579589844, "adapter_response": {}, "message": null, "failures": null, "unique_id": "test.twitter_ads_source.not_null_stg_twitter_ads__campaign_report_placement.5067d8c4f4"}, {"status": "success", "timing": [{"name": "compile", "started_at": "2023-09-05T23:42:23.385307Z", "completed_at": "2023-09-05T23:42:23.392901Z"}, {"name": "execute", "started_at": "2023-09-05T23:42:23.394502Z", "completed_at": "2023-09-05T23:42:23.394506Z"}], "thread_id": "Thread-8", "execution_time": 0.016501903533935547, "adapter_response": {}, "message": null, "failures": null, "unique_id": "test.twitter_ads_source.dbt_utils_unique_combination_of_columns_stg_twitter_ads__promoted_tweet_history_source_relation__promoted_tweet_id__updated_timestamp.7016099e0a"}, {"status": "success", "timing": [{"name": "compile", "started_at": "2023-09-05T23:42:23.389384Z", "completed_at": "2023-09-05T23:42:23.393676Z"}, {"name": "execute", "started_at": "2023-09-05T23:42:23.395949Z", "completed_at": "2023-09-05T23:42:23.395952Z"}], "thread_id": "Thread-1", "execution_time": 0.008465290069580078, "adapter_response": {}, "message": null, "failures": null, "unique_id": "test.twitter_ads_source.not_null_stg_twitter_ads__promoted_tweet_history_promoted_tweet_id.f447a1cd09"}, {"status": "success", "timing": [{"name": "compile", "started_at": "2023-09-05T23:42:23.398416Z", "completed_at": "2023-09-05T23:42:23.410429Z"}, {"name": "execute", "started_at": "2023-09-05T23:42:23.410827Z", "completed_at": "2023-09-05T23:42:23.410832Z"}], "thread_id": "Thread-2", "execution_time": 0.014816999435424805, "adapter_response": {}, "message": null, "failures": null, "unique_id": "test.twitter_ads_source.dbt_utils_unique_combination_of_columns_stg_twitter_ads__line_item_history_source_relation__line_item_id__updated_timestamp.646fa5270f"}, {"status": "success", "timing": [{"name": "compile", "started_at": "2023-09-05T23:42:23.402135Z", "completed_at": "2023-09-05T23:42:23.414594Z"}, {"name": "execute", "started_at": "2023-09-05T23:42:23.415942Z", "completed_at": "2023-09-05T23:42:23.415946Z"}], "thread_id": "Thread-5", "execution_time": 0.01956319808959961, "adapter_response": {}, "message": null, "failures": null, "unique_id": "test.twitter_ads_source.not_null_stg_twitter_ads__line_item_history_line_item_id.2cef040809"}, {"status": "success", "timing": [{"name": "compile", "started_at": "2023-09-05T23:42:23.404497Z", "completed_at": "2023-09-05T23:42:23.414831Z"}, {"name": "execute", "started_at": "2023-09-05T23:42:23.416141Z", "completed_at": "2023-09-05T23:42:23.416144Z"}], "thread_id": "Thread-8", "execution_time": 0.019484996795654297, "adapter_response": {}, "message": null, "failures": null, "unique_id": "test.twitter_ads.dbt_utils_unique_combination_of_columns_twitter_ads__account_report_source_relation__date_day__account_id__placement.e6a884489c"}, {"status": "success", "timing": [{"name": "compile", "started_at": "2023-09-05T23:42:23.408105Z", "completed_at": "2023-09-05T23:42:23.415037Z"}, {"name": "execute", "started_at": "2023-09-05T23:42:23.416337Z", "completed_at": "2023-09-05T23:42:23.416340Z"}], "thread_id": "Thread-1", "execution_time": 0.015958070755004883, "adapter_response": {}, "message": null, "failures": null, "unique_id": "test.twitter_ads.not_null_twitter_ads__account_report_account_id.90d5808908"}, {"status": "success", "timing": [{"name": "compile", "started_at": "2023-09-05T23:42:22.433091Z", "completed_at": "2023-09-05T23:42:23.330334Z"}, {"name": "execute", "started_at": "2023-09-05T23:42:23.349958Z", "completed_at": "2023-09-05T23:42:23.349967Z"}], "thread_id": "Thread-3", "execution_time": 0.9918420314788818, "adapter_response": {}, "message": null, "failures": null, "unique_id": "model.twitter_ads_source.stg_twitter_ads__line_item_report"}, {"status": "success", "timing": [{"name": "compile", "started_at": "2023-09-05T23:42:23.412211Z", "completed_at": "2023-09-05T23:42:23.415752Z"}, {"name": "execute", "started_at": "2023-09-05T23:42:23.418058Z", "completed_at": "2023-09-05T23:42:23.418061Z"}], "thread_id": "Thread-2", "execution_time": 0.007781982421875, "adapter_response": {}, "message": null, "failures": null, "unique_id": "test.twitter_ads.not_null_twitter_ads__account_report_date_day.84896c5846"}, {"status": "success", "timing": [{"name": "compile", "started_at": "2023-09-05T23:42:22.436896Z", "completed_at": "2023-09-05T23:42:23.350982Z"}, {"name": "execute", "started_at": "2023-09-05T23:42:23.356541Z", "completed_at": "2023-09-05T23:42:23.356545Z"}], "thread_id": "Thread-4", "execution_time": 1.0047411918640137, "adapter_response": {}, "message": null, "failures": null, "unique_id": "model.twitter_ads_source.stg_twitter_ads__line_item_keywords_report"}, {"status": "success", "timing": [{"name": "compile", "started_at": "2023-09-05T23:42:23.425370Z", "completed_at": "2023-09-05T23:42:23.437324Z"}, {"name": "execute", "started_at": "2023-09-05T23:42:23.439703Z", "completed_at": "2023-09-05T23:42:23.439708Z"}], "thread_id": "Thread-8", "execution_time": 0.020932912826538086, "adapter_response": {}, "message": null, "failures": null, "unique_id": "test.twitter_ads.dbt_utils_unique_combination_of_columns_twitter_ads__campaign_report_source_relation__date_day__campaign_id__placement__account_id.f449ef6d6e"}, {"status": "success", "timing": [{"name": "compile", "started_at": "2023-09-05T23:42:23.422208Z", "completed_at": "2023-09-05T23:42:23.437798Z"}, {"name": "execute", "started_at": "2023-09-05T23:42:23.440081Z", "completed_at": "2023-09-05T23:42:23.440083Z"}], "thread_id": "Thread-5", "execution_time": 0.026021718978881836, "adapter_response": {}, "message": null, "failures": null, "unique_id": "test.twitter_ads.not_null_twitter_ads__account_report_placement.157dcb6194"}, {"status": "success", "timing": [{"name": "compile", "started_at": "2023-09-05T23:42:23.429135Z", "completed_at": "2023-09-05T23:42:23.437993Z"}, {"name": "execute", "started_at": "2023-09-05T23:42:23.440432Z", "completed_at": "2023-09-05T23:42:23.440435Z"}], "thread_id": "Thread-1", "execution_time": 0.026159048080444336, "adapter_response": {}, "message": null, "failures": null, "unique_id": "test.twitter_ads.not_null_twitter_ads__campaign_report_campaign_id.03b1c451b8"}, {"status": "success", "timing": [{"name": "compile", "started_at": "2023-09-05T23:42:23.432611Z", "completed_at": "2023-09-05T23:42:23.439129Z"}, {"name": "execute", "started_at": "2023-09-05T23:42:23.445991Z", "completed_at": "2023-09-05T23:42:23.445995Z"}], "thread_id": "Thread-3", "execution_time": 0.025945186614990234, "adapter_response": {}, "message": null, "failures": null, "unique_id": "test.twitter_ads.not_null_twitter_ads__campaign_report_date_day.2b30b279b0"}, {"status": "success", "timing": [{"name": "compile", "started_at": "2023-09-05T23:42:23.435054Z", "completed_at": "2023-09-05T23:42:23.439497Z"}, {"name": "execute", "started_at": "2023-09-05T23:42:23.446709Z", "completed_at": "2023-09-05T23:42:23.446713Z"}], "thread_id": "Thread-2", "execution_time": 0.026278972625732422, "adapter_response": {}, "message": null, "failures": null, "unique_id": "test.twitter_ads.not_null_twitter_ads__campaign_report_placement.c66d252e82"}, {"status": "success", "timing": [{"name": "compile", "started_at": "2023-09-05T23:42:23.441193Z", "completed_at": "2023-09-05T23:42:23.448780Z"}, {"name": "execute", "started_at": "2023-09-05T23:42:23.455446Z", "completed_at": "2023-09-05T23:42:23.455451Z"}], "thread_id": "Thread-4", "execution_time": 0.022271156311035156, "adapter_response": {}, "message": null, "failures": null, "unique_id": "model.twitter_ads.twitter_ads__line_item_report"}, {"status": "success", "timing": [{"name": "compile", "started_at": "2023-09-05T23:42:23.451232Z", "completed_at": "2023-09-05T23:42:23.468002Z"}, {"name": "execute", "started_at": "2023-09-05T23:42:23.470380Z", "completed_at": "2023-09-05T23:42:23.470385Z"}], "thread_id": "Thread-8", "execution_time": 0.0231170654296875, "adapter_response": {}, "message": null, "failures": null, "unique_id": "test.twitter_ads_source.dbt_utils_unique_combination_of_columns_stg_twitter_ads__line_item_report_source_relation__date_day__line_item_id__placement.6c8686e61c"}, {"status": "success", "timing": [{"name": "compile", "started_at": "2023-09-05T23:42:23.455667Z", "completed_at": "2023-09-05T23:42:23.468460Z"}, {"name": "execute", "started_at": "2023-09-05T23:42:23.470905Z", "completed_at": "2023-09-05T23:42:23.470908Z"}], "thread_id": "Thread-5", "execution_time": 0.026547908782958984, "adapter_response": {}, "message": null, "failures": null, "unique_id": "test.twitter_ads_source.not_null_stg_twitter_ads__line_item_report_date_day.0f4d8cc8fe"}, {"status": "success", "timing": [{"name": "compile", "started_at": "2023-09-05T23:42:23.458182Z", "completed_at": "2023-09-05T23:42:23.468837Z"}, {"name": "execute", "started_at": "2023-09-05T23:42:23.471258Z", "completed_at": "2023-09-05T23:42:23.471261Z"}], "thread_id": "Thread-1", "execution_time": 0.026663780212402344, "adapter_response": {}, "message": null, "failures": null, "unique_id": "test.twitter_ads_source.not_null_stg_twitter_ads__line_item_report_line_item_id.9f5a4860b7"}, {"status": "success", "timing": [{"name": "compile", "started_at": "2023-09-05T23:42:23.463595Z", "completed_at": "2023-09-05T23:42:23.469657Z"}, {"name": "execute", "started_at": "2023-09-05T23:42:23.475144Z", "completed_at": "2023-09-05T23:42:23.475148Z"}], "thread_id": "Thread-2", "execution_time": 0.02588677406311035, "adapter_response": {}, "message": null, "failures": null, "unique_id": "model.twitter_ads.twitter_ads__keyword_report"}, {"status": "success", "timing": [{"name": "compile", "started_at": "2023-09-05T23:42:23.461152Z", "completed_at": "2023-09-05T23:42:23.470019Z"}, {"name": "execute", "started_at": "2023-09-05T23:42:23.475791Z", "completed_at": "2023-09-05T23:42:23.475794Z"}], "thread_id": "Thread-3", "execution_time": 0.026998043060302734, "adapter_response": {}, "message": null, "failures": null, "unique_id": "test.twitter_ads_source.not_null_stg_twitter_ads__line_item_report_placement.cd7e77e0eb"}, {"status": "success", "timing": [{"name": "compile", "started_at": "2023-09-05T23:42:23.471857Z", "completed_at": "2023-09-05T23:42:23.478003Z"}, {"name": "execute", "started_at": "2023-09-05T23:42:23.480833Z", "completed_at": "2023-09-05T23:42:23.480837Z"}], "thread_id": "Thread-4", "execution_time": 0.021711111068725586, "adapter_response": {}, "message": null, "failures": null, "unique_id": "test.twitter_ads_source.dbt_utils_unique_combination_of_columns_stg_twitter_ads__line_item_keywords_report_source_relation__date_day__keyword_id.579bdc1f1c"}, {"status": "success", "timing": [{"name": "compile", "started_at": "2023-09-05T23:42:23.481048Z", "completed_at": "2023-09-05T23:42:23.493762Z"}, {"name": "execute", "started_at": "2023-09-05T23:42:23.498015Z", "completed_at": "2023-09-05T23:42:23.498020Z"}], "thread_id": "Thread-8", "execution_time": 0.021127939224243164, "adapter_response": {}, "message": null, "failures": null, "unique_id": "test.twitter_ads_source.not_null_stg_twitter_ads__line_item_keywords_report_date_day.c7e7155b13"}, {"status": "success", "timing": [{"name": "compile", "started_at": "2023-09-05T23:42:23.484427Z", "completed_at": "2023-09-05T23:42:23.496340Z"}, {"name": "execute", "started_at": "2023-09-05T23:42:23.498641Z", "completed_at": "2023-09-05T23:42:23.498644Z"}], "thread_id": "Thread-5", "execution_time": 0.02140498161315918, "adapter_response": {}, "message": null, "failures": null, "unique_id": "test.twitter_ads_source.not_null_stg_twitter_ads__line_item_keywords_report_keyword_id.e5f015e9ec"}, {"status": "success", "timing": [{"name": "compile", "started_at": "2023-09-05T23:42:23.486927Z", "completed_at": "2023-09-05T23:42:23.497033Z"}, {"name": "execute", "started_at": "2023-09-05T23:42:23.499587Z", "completed_at": "2023-09-05T23:42:23.499591Z"}], "thread_id": "Thread-1", "execution_time": 0.02480912208557129, "adapter_response": {}, "message": null, "failures": null, "unique_id": "test.twitter_ads.dbt_utils_unique_combination_of_columns_twitter_ads__line_item_report_source_relation__date_day__line_item_id__placement__campaign_id__account_id.f8d7069cba"}, {"status": "success", "timing": [{"name": "compile", "started_at": "2023-09-05T23:42:23.491338Z", "completed_at": "2023-09-05T23:42:23.497805Z"}, {"name": "execute", "started_at": "2023-09-05T23:42:23.503497Z", "completed_at": "2023-09-05T23:42:23.503502Z"}], "thread_id": "Thread-2", "execution_time": 0.02507615089416504, "adapter_response": {}, "message": null, "failures": null, "unique_id": "test.twitter_ads.not_null_twitter_ads__line_item_report_date_day.86c934e8ce"}, {"status": "success", "timing": [{"name": "compile", "started_at": "2023-09-05T23:42:23.493979Z", "completed_at": "2023-09-05T23:42:23.498440Z"}, {"name": "execute", "started_at": "2023-09-05T23:42:23.504382Z", "completed_at": "2023-09-05T23:42:23.504386Z"}], "thread_id": "Thread-3", "execution_time": 0.025609970092773438, "adapter_response": {}, "message": null, "failures": null, "unique_id": "test.twitter_ads.not_null_twitter_ads__line_item_report_line_item_id.0462d58211"}, {"status": "success", "timing": [{"name": "compile", "started_at": "2023-09-05T23:42:23.500386Z", "completed_at": "2023-09-05T23:42:23.506564Z"}, {"name": "execute", "started_at": "2023-09-05T23:42:23.513591Z", "completed_at": "2023-09-05T23:42:23.513596Z"}], "thread_id": "Thread-4", "execution_time": 0.01884913444519043, "adapter_response": {}, "message": null, "failures": null, "unique_id": "test.twitter_ads.not_null_twitter_ads__line_item_report_placement.f103369312"}, {"status": "success", "timing": [{"name": "compile", "started_at": "2023-09-05T23:42:23.511266Z", "completed_at": "2023-09-05T23:42:23.516744Z"}, {"name": "execute", "started_at": "2023-09-05T23:42:23.517533Z", "completed_at": "2023-09-05T23:42:23.517537Z"}], "thread_id": "Thread-5", "execution_time": 0.012022972106933594, "adapter_response": {}, "message": null, "failures": null, "unique_id": "test.twitter_ads.not_null_twitter_ads__keyword_report_date_day.e0ce90c1ec"}, {"status": "success", "timing": [{"name": "compile", "started_at": "2023-09-05T23:42:23.507627Z", "completed_at": "2023-09-05T23:42:23.516967Z"}, {"name": "execute", "started_at": "2023-09-05T23:42:23.517924Z", "completed_at": "2023-09-05T23:42:23.517927Z"}], "thread_id": "Thread-8", "execution_time": 0.013571977615356445, "adapter_response": {}, "message": null, "failures": null, "unique_id": "test.twitter_ads.dbt_utils_unique_combination_of_columns_twitter_ads__keyword_report_source_relation__date_day__keyword_id__campaign_id.c51ddef475"}, {"status": "success", "timing": [{"name": "compile", "started_at": "2023-09-05T23:42:23.513845Z", "completed_at": "2023-09-05T23:42:23.517729Z"}, {"name": "execute", "started_at": "2023-09-05T23:42:23.519178Z", "completed_at": "2023-09-05T23:42:23.519181Z"}], "thread_id": "Thread-1", "execution_time": 0.01262521743774414, "adapter_response": {}, "message": null, "failures": null, "unique_id": "test.twitter_ads.not_null_twitter_ads__keyword_report_keyword_id.91efa0a538"}, {"status": "success", "timing": [{"name": "compile", "started_at": "2023-09-05T23:42:23.269857Z", "completed_at": "2023-09-05T23:42:24.086124Z"}, {"name": "execute", "started_at": "2023-09-05T23:42:24.087922Z", "completed_at": "2023-09-05T23:42:24.087929Z"}], "thread_id": "Thread-7", "execution_time": 0.9092369079589844, "adapter_response": {}, "message": null, "failures": null, "unique_id": "model.twitter_ads_source.stg_twitter_ads__tweet"}, {"status": "success", "timing": [{"name": "compile", "started_at": "2023-09-05T23:42:23.274095Z", "completed_at": "2023-09-05T23:42:24.088489Z"}, {"name": "execute", "started_at": "2023-09-05T23:42:24.088946Z", "completed_at": "2023-09-05T23:42:24.088950Z"}], "thread_id": "Thread-6", "execution_time": 0.9311261177062988, "adapter_response": {}, "message": null, "failures": null, "unique_id": "model.twitter_ads_source.stg_twitter_ads__tweet_url"}, {"status": "success", "timing": [{"name": "compile", "started_at": "2023-09-05T23:42:24.181296Z", "completed_at": "2023-09-05T23:42:24.200502Z"}, {"name": "execute", "started_at": "2023-09-05T23:42:24.202800Z", "completed_at": "2023-09-05T23:42:24.202804Z"}], "thread_id": "Thread-2", "execution_time": 0.02643108367919922, "adapter_response": {}, "message": null, "failures": null, "unique_id": "model.twitter_ads.twitter_ads__promoted_tweet_report"}, {"status": "success", "timing": [{"name": "compile", "started_at": "2023-09-05T23:42:24.192095Z", "completed_at": "2023-09-05T23:42:24.200996Z"}, {"name": "execute", "started_at": "2023-09-05T23:42:24.204038Z", "completed_at": "2023-09-05T23:42:24.204043Z"}], "thread_id": "Thread-3", "execution_time": 0.026742935180664062, "adapter_response": {}, "message": null, "failures": null, "unique_id": "test.twitter_ads_source.dbt_utils_unique_combination_of_columns_stg_twitter_ads__tweet_source_relation__tweet_id.70de7f05f5"}, {"status": "success", "timing": [{"name": "compile", "started_at": "2023-09-05T23:42:24.196484Z", "completed_at": "2023-09-05T23:42:24.201461Z"}, {"name": "execute", "started_at": "2023-09-05T23:42:24.205598Z", "completed_at": "2023-09-05T23:42:24.205602Z"}], "thread_id": "Thread-4", "execution_time": 0.026887893676757812, "adapter_response": {}, "message": null, "failures": null, "unique_id": "test.twitter_ads_source.not_null_stg_twitter_ads__tweet_tweet_id.a0427f37cd"}, {"status": "success", "timing": [{"name": "compile", "started_at": "2023-09-05T23:42:24.219472Z", "completed_at": "2023-09-05T23:42:24.248967Z"}, {"name": "execute", "started_at": "2023-09-05T23:42:24.259708Z", "completed_at": "2023-09-05T23:42:24.259713Z"}], "thread_id": "Thread-7", "execution_time": 0.05684089660644531, "adapter_response": {}, "message": null, "failures": null, "unique_id": "test.twitter_ads_source.not_null_stg_twitter_ads__tweet_url_index.e998fb67be"}, {"status": "success", "timing": [{"name": "compile", "started_at": "2023-09-05T23:42:24.214290Z", "completed_at": "2023-09-05T23:42:24.249259Z"}, {"name": "execute", "started_at": "2023-09-05T23:42:24.259927Z", "completed_at": "2023-09-05T23:42:24.259930Z"}], "thread_id": "Thread-1", "execution_time": 0.057936906814575195, "adapter_response": {}, "message": null, "failures": null, "unique_id": "test.twitter_ads_source.dbt_utils_unique_combination_of_columns_stg_twitter_ads__tweet_url_source_relation__index__tweet_id.ce1a2b4a87"}, {"status": "success", "timing": [{"name": "compile", "started_at": "2023-09-05T23:42:24.207992Z", "completed_at": "2023-09-05T23:42:24.249612Z"}, {"name": "execute", "started_at": "2023-09-05T23:42:24.260189Z", "completed_at": "2023-09-05T23:42:24.260193Z"}], "thread_id": "Thread-8", "execution_time": 0.05919003486633301, "adapter_response": {}, "message": null, "failures": null, "unique_id": "model.twitter_ads.twitter_ads__url_report"}, {"status": "success", "timing": [{"name": "compile", "started_at": "2023-09-05T23:42:24.222802Z", "completed_at": "2023-09-05T23:42:24.250023Z"}, {"name": "execute", "started_at": "2023-09-05T23:42:24.260458Z", "completed_at": "2023-09-05T23:42:24.260463Z"}], "thread_id": "Thread-5", "execution_time": 0.05817008018493652, "adapter_response": {}, "message": null, "failures": null, "unique_id": "test.twitter_ads_source.not_null_stg_twitter_ads__tweet_url_tweet_id.f7e1670218"}, {"status": "success", "timing": [{"name": "compile", "started_at": "2023-09-05T23:42:24.250228Z", "completed_at": "2023-09-05T23:42:24.260708Z"}, {"name": "execute", "started_at": "2023-09-05T23:42:24.264461Z", "completed_at": "2023-09-05T23:42:24.264464Z"}], "thread_id": "Thread-6", "execution_time": 0.018948078155517578, "adapter_response": {}, "message": null, "failures": null, "unique_id": "test.twitter_ads.dbt_utils_unique_combination_of_columns_twitter_ads__promoted_tweet_report_source_relation__date_day__promoted_tweet_id__placement__line_item_id__campaign_id__account_id.f6814a1cc6"}, {"status": "success", "timing": [{"name": "compile", "started_at": "2023-09-05T23:42:24.254751Z", "completed_at": "2023-09-05T23:42:24.261895Z"}, {"name": "execute", "started_at": "2023-09-05T23:42:24.264989Z", "completed_at": "2023-09-05T23:42:24.264992Z"}], "thread_id": "Thread-2", "execution_time": 0.01978015899658203, "adapter_response": {}, "message": null, "failures": null, "unique_id": "test.twitter_ads.not_null_twitter_ads__promoted_tweet_report_placement.d89c9b27e5"}, {"status": "success", "timing": [{"name": "compile", "started_at": "2023-09-05T23:42:24.257225Z", "completed_at": "2023-09-05T23:42:24.262101Z"}, {"name": "execute", "started_at": "2023-09-05T23:42:24.265185Z", "completed_at": "2023-09-05T23:42:24.265188Z"}], "thread_id": "Thread-3", "execution_time": 0.019804954528808594, "adapter_response": {}, "message": null, "failures": null, "unique_id": "test.twitter_ads.not_null_twitter_ads__promoted_tweet_report_promoted_tweet_id.5df08e154e"}, {"status": "success", "timing": [{"name": "compile", "started_at": "2023-09-05T23:42:24.273387Z", "completed_at": "2023-09-05T23:42:24.283623Z"}, {"name": "execute", "started_at": "2023-09-05T23:42:24.284029Z", "completed_at": "2023-09-05T23:42:24.284033Z"}], "thread_id": "Thread-4", "execution_time": 0.01871323585510254, "adapter_response": {}, "message": null, "failures": null, "unique_id": "test.twitter_ads.not_null_twitter_ads__url_report_base_url.dfd7ab549e"}, {"status": "success", "timing": [{"name": "compile", "started_at": "2023-09-05T23:42:24.276490Z", "completed_at": "2023-09-05T23:42:24.284672Z"}, {"name": "execute", "started_at": "2023-09-05T23:42:24.285950Z", "completed_at": "2023-09-05T23:42:24.285953Z"}], "thread_id": "Thread-7", "execution_time": 0.020859956741333008, "adapter_response": {}, "message": null, "failures": null, "unique_id": "test.twitter_ads.not_null_twitter_ads__url_report_date_day.33fcb7e04b"}, {"status": "success", "timing": [{"name": "compile", "started_at": "2023-09-05T23:42:24.278757Z", "completed_at": "2023-09-05T23:42:24.284893Z"}, {"name": "execute", "started_at": "2023-09-05T23:42:24.286486Z", "completed_at": "2023-09-05T23:42:24.286489Z"}], "thread_id": "Thread-1", "execution_time": 0.020992040634155273, "adapter_response": {}, "message": null, "failures": null, "unique_id": "test.twitter_ads.not_null_twitter_ads__url_report_placement.92ca3b192e"}, {"status": "success", "timing": [{"name": "compile", "started_at": "2023-09-05T23:42:24.280968Z", "completed_at": "2023-09-05T23:42:24.285359Z"}, {"name": "execute", "started_at": "2023-09-05T23:42:24.287090Z", "completed_at": "2023-09-05T23:42:24.287094Z"}], "thread_id": "Thread-8", "execution_time": 0.021130084991455078, "adapter_response": {}, "message": null, "failures": null, "unique_id": "test.twitter_ads.not_null_twitter_ads__url_report_promoted_tweet_id.d690f99143"}, {"status": "success", "timing": [{"name": "compile", "started_at": "2023-09-05T23:42:24.269178Z", "completed_at": "2023-09-05T23:42:24.285565Z"}, {"name": "execute", "started_at": "2023-09-05T23:42:24.287296Z", "completed_at": "2023-09-05T23:42:24.287300Z"}], "thread_id": "Thread-5", "execution_time": 0.023099899291992188, "adapter_response": {}, "message": null, "failures": null, "unique_id": "test.twitter_ads.dbt_utils_unique_combination_of_columns_twitter_ads__url_report_source_relation__date_day__promoted_tweet_id__placement__line_item_id__campaign_id__account_id.f44851c31f"}], "elapsed_time": 4.567528247833252, "args": {"log_file_max_bytes": 10485760, "indirect_selection": "eager", "introspect": true, "use_colors_file": true, "exclude": [], "static_parser": true, "printer_width": 80, "select": [], "which": "generate", "write_json": true, "log_format_file": "debug", "partial_parse": true, "project_dir": "/Users/catherinefritz/Documents/dbt_packages/twitter/dbt_twitter/integration_tests", "cache_selected_only": false, "log_format": "default", "print": true, "strict_mode": false, "enable_legacy_logger": false, "vars": {}, "log_path": "/Users/catherinefritz/Documents/dbt_packages/twitter/dbt_twitter/integration_tests/logs", "quiet": false, "profiles_dir": "/Users/catherinefritz/.dbt", "defer": false, "use_colors": true, "populate_cache": true, "warn_error_options": {"include": [], "exclude": []}, "compile": true, "macro_debugging": false, "log_level": "info", "send_anonymous_usage_stats": true, "log_level_file": "debug", "favor_state": false, "version_check": true}}